odoo/addons/auth_u2f/LICENSE.txt
odoo/addons/auth_u2f/README.rst
odoo/addons/auth_u2f/__init__.py
odoo/addons/auth_u2f/__manifest__.py
odoo/addons/auth_u2f/controllers/__init__.py
odoo/addons/auth_u2f/controllers/main.py
odoo/addons/auth_u2f/i18n/auth_u2f.pot
odoo/addons/auth_u2f/models/__init__.py
odoo/addons/auth_u2f/models/http.py
odoo/addons/auth_u2f/models/res_users.py
odoo/addons/auth_u2f/models/u2f_device.py
odoo/addons/auth_u2f/readme/DESCRIPTION.rst
odoo/addons/auth_u2f/readme/INSTALL.rst
odoo/addons/auth_u2f/readme/USAGE.rst
odoo/addons/auth_u2f/security/auth_u2f_security.xml
odoo/addons/auth_u2f/security/ir.model.access.csv
odoo/addons/auth_u2f/static/description/icon.png
odoo/addons/auth_u2f/static/description/index.html
odoo/addons/auth_u2f/static/lib/u2f-api.js
odoo/addons/auth_u2f/static/src/js/auth_u2f.js
odoo/addons/auth_u2f/static/src/js/auth_u2f_frontend.js
odoo/addons/auth_u2f/tests/__init__.py
odoo/addons/auth_u2f/tests/test_device.py
odoo/addons/auth_u2f/tests/test_http.py
odoo/addons/auth_u2f/tests/test_main.py
odoo/addons/auth_u2f/tests/test_users.py
odoo/addons/auth_u2f/views/res_users.xml
odoo/addons/auth_u2f/views/u2f_device.xml
odoo/addons/auth_u2f/views/u2f_templates.xml
odoo12_addon_auth_u2f-12.0.1.0.2.dist-info/METADATA
odoo12_addon_auth_u2f-12.0.1.0.2.dist-info/WHEEL
odoo12_addon_auth_u2f-12.0.1.0.2.dist-info/top_level.txt
odoo12_addon_auth_u2f-12.0.1.0.2.dist-info/RECORD
