Metadata-Version: 2.1
Name: odoo12-addon-auth-u2f
Version: 12.0.1.0.2
Summary: 2nd factor authentication via U2F devices
Home-page: https://github.com/OCA/server-auth
Author: Joren Van Onder, initOS GmbH, Odoo Community Association (OCA)
Author-email: support@odoo-community.org
License: LGPL-3
Platform: UNKNOWN
Classifier: Programming Language :: Python
Classifier: Framework :: Odoo
Classifier: Framework :: Odoo :: 12.0
Classifier: License :: OSI Approved :: GNU Lesser General Public License v3 (LGPLv3)
Requires-Python: >=3.5
Requires-Dist: cryptography (<37)
Requires-Dist: odoo (<12.1dev,>=12.0a)
Requires-Dist: python-u2flib-server
